Metadata-Version: 2.1
Name: nautobot-type-reapply
Version: 1.0.0
Summary: A Nautobot plugin for re-appling device types
Home-page: https://gitlab-ce.gwdg.de/gwdg-netz/nautobot-plugins/nautobot-type-reapply
Author: Gesellschaft für wissenschaftliche Datenverarbeitung mbH Göttingen
Author-email: netzadmin@gwdg.de
License: Apache-2.0
Platform: UNKNOWN
License-File: LICENSE.txt
